{
  "$schema": "https://dmfr.transit.land/json-schema/dmfr.schema-v0.5.1.json",
  "feeds": [
    {
      "id": "f-u09-île~de~france~mobilités",
      "spec": "gtfs",
      "urls": {
        "static_current": "https://eu.ftp.opendatasoft.com/stif/GTFS/IDFM-gtfs.zip",
        "static_historic": [
          "https://opendata.stif.info/explore/dataset/offre-horaires-tc-gtfs-idf/files/73abe383c9dd51e1d78be6e672a2da3a/download/"
        ]
      },
      "license": {
        "spdx_identifier": "ODbL-1.0",
        "url": "https://data.iledefrance-mobilites.fr/explore/dataset/offre-horaires-tc-gtfs-idfm/information/",
        "use_without_attribution": "no",
        "create_derived_product": "yes"
      }
    }
  ],
  "license_spdx_identifier": "CDLA-Permissive-1.0"
}
